pyams_sequence/__init__.py
pyams_sequence/include.py
pyams_sequence/interfaces.py
pyams_sequence/reference.py
pyams_sequence/schema.py
pyams_sequence/sequence.py
pyams_sequence/utility.py
pyams_sequence/workflow.py
pyams_sequence/api/__init__.py
pyams_sequence/api/rest.py
pyams_sequence/doctests/README.rst
pyams_sequence/generations/__init__.py
pyams_sequence/locales/pyams_sequence.pot
pyams_sequence/locales/fr/LC_MESSAGES/pyams_sequence.mo
pyams_sequence/locales/fr/LC_MESSAGES/pyams_sequence.po
pyams_sequence/tests/__init__.py
pyams_sequence/tests/test_utilsdocs.py
pyams_sequence/tests/test_utilsdocstrings.py
pyams_sequence/widget/__init__.py
pyams_sequence/widget/interfaces.py
pyams_sequence/zmi/__init__.py
pyams_sequence/zmi/reference.py
pyams_sequence-2.1.0.dist-info/LICENSE
pyams_sequence-2.1.0.dist-info/METADATA
pyams_sequence-2.1.0.dist-info/WHEEL
pyams_sequence-2.1.0.dist-info/namespace_packages.txt
pyams_sequence-2.1.0.dist-info/top_level.txt
pyams_sequence-2.1.0.dist-info/RECORD
