Metadata-Version: 2.1
Name: pyams-sequence
Version: 2.1.0
Summary: PyAMS sequences management package
Home-page: https://pyams.readthedocs.io
Author: Thierry Florac
Author-email: tflorac@ulthar.net
License: ZPL
Keywords: Pyramid PyAMS
Classifier: License :: OSI Approved :: Zope Public License
Classifier: Development Status :: 4 - Beta
Classifier: Programming Language :: Python
Classifier: Framework :: Pyramid
Classifier: Topic :: Software Development :: Libraries :: Python Modules
License-File: LICENSE
Requires-Dist: setuptools
Requires-Dist: colander
Requires-Dist: cornice
Requires-Dist: hypatia
Requires-Dist: persistent
Requires-Dist: pyams-catalog
Requires-Dist: pyams-form
Requires-Dist: pyams-i18n
Requires-Dist: pyams-layer
Requires-Dist: pyams-security
Requires-Dist: pyams-site
Requires-Dist: pyams-skin
Requires-Dist: pyams-utils
Requires-Dist: pyams-workflow
Requires-Dist: pyramid >=2.0.0
Requires-Dist: zope.annotation
Requires-Dist: zope.interface
Requires-Dist: zope.intid
Requires-Dist: zope.lifecycleevent
Requires-Dist: zope.schema
Provides-Extra: test
Requires-Dist: pyams-zmi ; extra == 'test'
Requires-Dist: pyramid-zcml ; extra == 'test'
Requires-Dist: zope.exceptions ; extra == 'test'
